{
  "$schema": "https://raw.githubusercontent.com/Azure/azure-dev/main/cli/azd/extensions/registry.schema.json",
  "extensions": [
    {
      "id": "jongio.azd.app",
      "namespace": "app",
      "displayName": "App Extension",
      "description": "A collection of developer productivity commands for Azure Developer CLI",
      "publisher": "jongio",
      "tags": [
        "developer",
        "productivity",
        "app"
      ],
      "versions": [
        {
          "version": "0.1.1",
          "capabilities": [
            "custom-commands"
          ],
          "usage": "azd app <command> [options]",
          "examples": [
            {
              "name": "reqs",
              "description": "Check for required prerequisites",
              "usage": "azd app reqs"
            },
            {
              "name": "deps",
              "description": "Install dependencies for all detected projects",
              "usage": "azd app deps"
            },
            {
              "name": "run",
              "description": "Run the development environment (services from azure.yaml, Aspire, pnpm, or docker compose)",
              "usage": "azd app run"
            },
            {
              "name": "logs",
              "description": "View logs from running services",
              "usage": "azd app logs [service-name]"
            },
            {
              "name": "info",
              "description": "Show information about running services",
              "usage": "azd app info"
            },
            {
              "name": "version",
              "description": "Show version information",
              "usage": "azd app version"
            }
          ],
          "entryPoint": "app",
          "artifacts": {
            "windows/amd64": {
              "url": "https://github.com/jongio/azd-app/releases/download/azd-app-cli-v0.1.1/app-windows-amd64.zip",
              "checksum": {
                "algorithm": "sha256",
                "value": "61ac155a59ba369352e3eb4f42e6a18a786b047477638cc0d8461fa85279ad8b"
              },
              "entryPoint": "app.exe"
            },
            "linux/amd64": {
              "url": "https://github.com/jongio/azd-app/releases/download/azd-app-cli-v0.1.1/app-linux-amd64.tar.gz",
              "checksum": {
                "algorithm": "sha256",
                "value": "b2c9aaf3dcd9bc6fcf6fff0918a95c31dfd4372ab6046070bff19d40fd753705"
              },
              "entryPoint": "app"
            },
            "darwin/amd64": {
              "url": "https://github.com/jongio/azd-app/releases/download/azd-app-cli-v0.1.1/app-darwin-amd64.tar.gz",
              "checksum": {
                "algorithm": "sha256",
                "value": "db74dd2972090b222b48d307288260d12aa2759b7de9b00bfa3b4adf60dde3c8"
              },
              "entryPoint": "app"
            },
            "darwin/arm64": {
              "url": "https://github.com/jongio/azd-app/releases/download/azd-app-cli-v0.1.1/app-darwin-arm64.tar.gz",
              "checksum": {
                "algorithm": "sha256",
                "value": "618def1a9811e6a1603fbdd65759aaa5400c273f0dec3b6d90e5fd228f6be131"
              },
              "entryPoint": "app"
            }
          }
        }
      ]
    }
  ]
}
